nicovideo_api_client/__init__.py
nicovideo_api_client/api/__init__.py
nicovideo_api_client/api/v2/__init__.py
nicovideo_api_client/api/v2/field.py
nicovideo_api_client/api/v2/filter.py
nicovideo_api_client/api/v2/json_filter.py
nicovideo_api_client/api/v2/limit.py
nicovideo_api_client/api/v2/request.py
nicovideo_api_client/api/v2/result.py
nicovideo_api_client/api/v2/simple_filter.py
nicovideo_api_client/api/v2/snapshot_search_api_v2.py
nicovideo_api_client/api/v2/sort.py
nicovideo_api_client/api/v2/targets.py
nicovideo_api_client/api/v2/user_agent.py
nicovideo_api_client/constants.py
nicovideo_api_client-3.0.1.dist-info/METADATA
nicovideo_api_client-3.0.1.dist-info/WHEEL
nicovideo_api_client-3.0.1.dist-info/RECORD
