Metadata-Version: 2.1
Name: nicovideo_api_client
Version: 3.0.1
Summary: ニコニコ動画 スナップショット検索APIv2の Python クライアント
Home-page: https://github.com/Javakky/NicoApiClient
Author: Javakky
Author-email: iemura.java@gmail.com
Requires-Python: >=3.10.2,<4.0.0
Classifier: Development Status :: 2 - Pre-Alpha
Classifier: Programming Language :: Python
Classifier: Programming Language :: Python :: 3
Classifier: Programming Language :: Python :: 3.11
Classifier: Programming Language :: Python :: 3.12
Classifier: Programming Language :: Python :: 3.13
Classifier: Programming Language :: Python :: 3.10
Requires-Dist: requests (>=2.26.0,<3.0.0)
Requires-Dist: urllib3 (>=1.26.6,<3.0.0)
